cutout/__init__.py
cutout/cleanup.py
cutout/constants.py
cutout/stencil.py
cut_out_cookies-0.3.1.dist-info/LICENSE.md
cut_out_cookies-0.3.1.dist-info/METADATA
cut_out_cookies-0.3.1.dist-info/WHEEL
cut_out_cookies-0.3.1.dist-info/RECORD
