Metadata-Version: 2.1
Name: cut-out-cookies
Version: 0.3.1
Summary: Jinja extension for optionally including files and directories
Home-page: https://github.com/dusktreader/cut-out-cookies
License: MIT
Author: Tucker Beck
Author-email: tucker.beck@gmail.com
Requires-Python: >=3.8,<4.0
Classifier: License :: OSI Approved :: MIT License
Classifier: Programming Language :: Python :: 3
Classifier: Programming Language :: Python :: 3.8
Classifier: Programming Language :: Python :: 3.9
Classifier: Programming Language :: Python :: 3.10
Classifier: Programming Language :: Python :: 3.11
Requires-Dist: Jinja2 (>=2.11.3,<3.1.0)
Project-URL: Repository, https://github.com/dusktreader/cut-out-cookies
